odoo/addons/ebill_postfinance_financial_discount/README.rst
odoo/addons/ebill_postfinance_financial_discount/__init__.py
odoo/addons/ebill_postfinance_financial_discount/__manifest__.py
odoo/addons/ebill_postfinance_financial_discount/i18n/ebill_postfinance_financial_discount.pot
odoo/addons/ebill_postfinance_financial_discount/messages/invoice-yellowbill-financial-discount.jinja
odoo/addons/ebill_postfinance_financial_discount/models/__init__.py
odoo/addons/ebill_postfinance_financial_discount/models/ebill_postfinance_invoice_message.py
odoo/addons/ebill_postfinance_financial_discount/readme/CONTRIBUTORS.rst
odoo/addons/ebill_postfinance_financial_discount/readme/DESCRIPTION.rst
odoo/addons/ebill_postfinance_financial_discount/static/description/icon.png
odoo/addons/ebill_postfinance_financial_discount/static/description/index.html
odoo/addons/ebill_postfinance_financial_discount/tests/__init__.py
odoo/addons/ebill_postfinance_financial_discount/tests/test_postfinance_financial_discount.py
odoo/addons/ebill_postfinance_financial_discount/tests/examples/invoice_qr_yb.xml
odoo14_addon_ebill_postfinance_financial_discount-14.0.1.0.1.dev3.dist-info/METADATA
odoo14_addon_ebill_postfinance_financial_discount-14.0.1.0.1.dev3.dist-info/WHEEL
odoo14_addon_ebill_postfinance_financial_discount-14.0.1.0.1.dev3.dist-info/top_level.txt
odoo14_addon_ebill_postfinance_financial_discount-14.0.1.0.1.dev3.dist-info/RECORD
