Metadata-Version: 2.1
Name: odoo14-addon-ebill_postfinance_financial_discount
Version: 14.0.1.0.1.dev3
Summary: Integrate the discount from account_financial_discount into ebill_postfinance
Home-page: https://github.com/OCA/l10n-switzerland
Author: Camptocamp,Odoo Community Association (OCA)
Author-email: support@odoo-community.org
License: AGPL-3
Classifier: Programming Language :: Python
Classifier: Framework :: Odoo
Classifier: Framework :: Odoo :: 14.0
Classifier: License :: OSI Approved :: GNU Affero General Public License v3
Requires-Python: >=3.6
Requires-Dist: odoo14-addon-account-financial-discount
Requires-Dist: odoo14-addon-ebill-postfinance
Requires-Dist: odoo<14.1dev,>=14.0a
